operate/__init__.py
operate/config.py
operate/exceptions.py
operate/main.py
operate/operate.py
operate/models/__init__.py
operate/models/apis.py
operate/models/model_configs.py
operate/models/prompts.py
operate/models/weights/__init__.py
operate/models/weights/best.pt
operate/utils/__init__.py
operate/utils/label.py
operate/utils/misc.py
operate/utils/ocr.py
operate/utils/operating_system.py
operate/utils/screenshot.py
operate/utils/style.py
self_ai_operating_computer-2.0.15.dist-info/licenses/LICENSE
self_ai_operating_computer-2.0.15.dist-info/METADATA
self_ai_operating_computer-2.0.15.dist-info/WHEEL
self_ai_operating_computer-2.0.15.dist-info/entry_points.txt
self_ai_operating_computer-2.0.15.dist-info/top_level.txt
self_ai_operating_computer-2.0.15.dist-info/RECORD
